alpaca_wrapper/__init__.py
alpaca_wrapper/base.py
alpaca_wrapper/market_data.py
alpaca_wrapper/trading.py
built_in_agents/__init__.py
built_in_agents/delta_hedger.py
built_in_agents/performance_tracker.py
built_in_agents/spotter.py
built_in_agents/spread_calculator.py
core/__init__.py
core/communication_bus.py
core/data_cache.py
core/trading_agent.py
core/trading_hub.py
data/__init__.py
data/data_types.py
trading_algo-0.1.3.dist-info/licenses/LICENSE
trading_algo-0.1.3.dist-info/METADATA
trading_algo-0.1.3.dist-info/WHEEL
trading_algo-0.1.3.dist-info/top_level.txt
trading_algo-0.1.3.dist-info/RECORD
