Metadata-Version: 2.4
Name: trading-algo
Version: 0.1.3
Summary: A flexible, event-driven, multi-agent framework for building algorithmic trading strategies using the Alpaca API.
Author-email: joshuaengindeniz <117681341+joshuaeng@users.noreply.github.com>
Project-URL: Homepage, https://github.com/joshuaengindeniz/tradingAlgo
Project-URL: Bug Tracker, https://github.com/joshuaengindeniz/tradingAlgo/issues
Classifier: Programming Language :: Python :: 3
Classifier: License :: OSI Approved :: MIT License
Classifier: Operating System :: OS Independent
Requires-Python: >=3.9
License-File: LICENSE
Requires-Dist: alpaca-py==0.42.1
Requires-Dist: annotated-types==0.7.0
Requires-Dist: certifi==2025.8.3
Requires-Dist: charset-normalizer==3.4.3
Requires-Dist: idna==3.10
Requires-Dist: msgpack==1.1.1
Requires-Dist: numpy
Requires-Dist: pandas
Requires-Dist: pydantic==2.11.7
Requires-Dist: pydantic_core==2.33.2
Requires-Dist: python-dateutil==2.9.0.post0
Requires-Dist: pytz==2025.2
Requires-Dist: requests==2.32.5
Requires-Dist: six==1.17.0
Requires-Dist: sseclient-py==1.8.0
Requires-Dist: typing-inspection==0.4.1
Requires-Dist: typing_extensions==4.15.0
Requires-Dist: tzdata==2025.2
Requires-Dist: urllib3==2.5.0
Requires-Dist: websockets==15.0.1
Requires-Dist: loguru~=0.7.3
Requires-Dist: matplotlib
Requires-Dist: multiprocess
Dynamic: license-file
